[
  {
    "id": "95b1f5d5-a96c-4cb9-9fa7-7592929588d5",
    "name": "Giselbert",
    "goal": "Zamit",
    "description": "j8nVx1El5ra0s5fgjuz4Ug4kE4p1sJgCKe92",
    "section": [
      {
        "name": "Glory",
        "project": "Vipe",
        "resources": "23400 Truax Park"
      },
      {
        "name": "Libbie",
        "project": "Yamia",
        "resources": "3557 International Road"
      },
      {
        "name": "Ileane",
        "project": "Browsecat",
        "resources": "74 Morrow Park"
      }
    ],
    "createdOn": "12/29/2020"
  },
  {
    "id": "084ad6e1-e52c-4a90-bc11-80d7d1fd1422",
    "name": "Katey",
    "goal": "Aerified",
    "description": "f46XrKDh1tc0v3yuu6w0L34iN8y22NrSQq5x",
    "section": [
      {
        "name": "Fedora",
        "project": "Flashpoint",
        "resources": "09792 Spohn Way"
      },
      {
        "name": "Pepi",
        "project": "Jabberbean",
        "resources": "1112 Namekagon Crossing"
      }
    ],
    "createdOn": "10/12/2020"
  },
  {
    "id": "bc9e7d5e-f4c4-4b7e-a375-638da9d5c115",
    "name": "Aylmar",
    "goal": "Rank",
    "description": "z2tTr2Ab8cg373yba4e9HxJpU6i13OuANk51",
    "section": [
      {
        "name": "Anica",
        "project": "Gabvine",
        "resources": "50943 Vermont Circle"
      },
      {
        "name": "Suzanne",
        "project": "Wikivu",
        "resources": "221 Blackbird Park"
      }
    ],
    "createdOn": "5/1/2020"
  },
  {
    "id": "f019f5ab-e586-480c-b5c3-be735c8a836b",
    "name": "Lyndy",
    "goal": "Ronstring",
    "description": "x08S50Li5zz2r5fyqci7I75fN3q54By5Ra55",
    "section": [
      {
        "name": "Christel",
        "project": "Thoughtworks",
        "resources": "155 Emmet Crossing"
      },
      {
        "name": "Birgitta",
        "project": "Kazu",
        "resources": "589 Sherman Place"
      },
      {
        "name": "Tiffanie",
        "project": "Skibox",
        "resources": "258 Grayhawk Circle"
      }
    ],
    "createdOn": "12/13/2020"
  },
  {
    "id": "d4aa3c88-46d5-4dec-b575-29dcc194da65",
    "name": "Audry",
    "goal": "Mat Lam Tam",
    "description": "d1gM0HPm7gc1v6b3ire3Ij9pT1e9pWdPMf02",
    "section": [
      {
        "name": "Vivie",
        "project": "Jazzy",
        "resources": "9 Loeprich Plaza"
      },
      {
        "name": "Jackie",
        "project": "Twitterbeat",
        "resources": "988 Rusk Court"
      }
    ],
    "createdOn": "6/7/2020"
  },
  {
    "id": "9413f059-bd63-459d-8b3e-528ba18ef717",
    "name": "Regine",
    "goal": "Daltfresh",
    "description": "t6aLxTUc1hw2o8zgctf0Bo4jN0b3dTmHFd99",
    "section": [
      {
        "name": "Rubetta",
        "project": "Livepath",
        "resources": "8869 Eastlawn Alley"
      },
      {
        "name": "Cherrita",
        "project": "Tazzy",
        "resources": "22 School Way"
      },
      {
        "name": "Melany",
        "project": "Yoveo",
        "resources": "342 Fremont Court"
      }
    ],
    "createdOn": "8/27/2020"
  },
  {
    "id": "f12216a0-77ee-47d4-928f-072c716c1810",
    "name": "Angelico",
    "goal": "Sub-Ex",
    "description": "z1fKxVSc1gi384c582w8NhPpI5m9rKf6Fk1f",
    "section": [
      {
        "name": "Flo",
        "project": "Realbridge",
        "resources": "00853 Carey Alley"
      },
      {
        "name": "Joan",
        "project": "Npath",
        "resources": "00 Goodland Avenue"
      },
      {
        "name": "Melloney",
        "project": "Zoonoodle",
        "resources": "53 Anzinger Point"
      }
    ],
    "createdOn": "10/28/2020"
  },
  {
    "id": "23c42fae-8935-4d13-b7b1-d76aa8ef44a2",
    "name": "Bertie",
    "goal": "Aerified",
    "description": "g30EaSMl1ab8i3snc2l7N79gE8q40Yc7Cc2q",
    "section": [
      {
        "name": "Tamarah",
        "project": "Browsedrive",
        "resources": "23960 Sauthoff Way"
      },
      {
        "name": null,
        "project": null,
        "resources": null
      },
      {
        "name": "Jocelyne",
        "project": "Mudo",
        "resources": "70005 Independence Drive"
      }
    ],
    "createdOn": "8/18/2020"
  },
  {
    "id": null,
    "name": null,
    "goal": null,
    "description": null,
    "section": null,
    "createdOn": null
  },
  {
    "id": "5f4b210b-5328-454d-9205-1203493e89a4",
    "name": "Katherine",
    "goal": "Prodder",
    "description": "p9eT57Km26k8j8jfiuq5Zo1gH8y29EnEAm8y",
    "section": [
      {
        "name": "Leshia",
        "project": "Eadel",
        "resources": "608 Mcbride Place"
      },
      {
        "name": "Viki",
        "project": "Meembee",
        "resources": "9963 Chive Avenue"
      },
      {
        "name": "Modestia",
        "project": "Oloo",
        "resources": "8 Vermont Place"
      }
    ],
    "createdOn": "8/26/2020"
  }
]